{
  "source_url": "https://www.giet.edu/wp-content/uploads/2025/12/B.-Sc.-Hons-Agriculture.-Form-Fill-up-Notice.pdf",
  "source_page": "https://www.giet.edu/examinations/notices/",
  "original_link_text": "B. Sc. (Hons) Agriculture. Form Fill up Notice",
  "scraped_at": 1770288447.4072356,
  "headers": {
    "Connection": "Keep-Alive",
    "Keep-Alive": "timeout=5, max=100",
    "Cache-Control": "public, max-age=31536000,public",
    "Expires": "Fri, 05 Feb 2027 10:47:27 GMT",
    "Content-Type": "application/pdf",
    "Last-Modified": "Mon, 29 Dec 2025 12:13:14 GMT",
    "Accept-Ranges": "bytes",
    "Content-Length": "609108",
    "Date": "Thu, 05 Feb 2026 10:47:27 GMT",
    "Server": "LiteSpeed",
    "Strict-Transport-Security": "max-age=63072000; includeSubDomains",
    "X-Frame-Options": "SAMEORIGIN",
    "X-Content-Type-Options": "nosniff",
    "Vary": "Accept-Encoding,User-Agent"
  }
}